sustainable_wage_tool_data/__init__.py
sustainable_wage_tool_data/__main__.py
sustainable_wage_tool_data-1.0.0.dev1.dist-info/LICENCE
sustainable_wage_tool_data-1.0.0.dev1.dist-info/METADATA
sustainable_wage_tool_data-1.0.0.dev1.dist-info/WHEEL
sustainable_wage_tool_data-1.0.0.dev1.dist-info/top_level.txt
sustainable_wage_tool_data-1.0.0.dev1.dist-info/RECORD
